swiftapi/__init__.py
swiftapi/authentication.py
swiftapi/browsable.py
swiftapi/bulk.py
swiftapi/caching.py
swiftapi/conf.py
swiftapi/content.py
swiftapi/crud.py
swiftapi/decorators.py
swiftapi/events.py
swiftapi/exceptions.py
swiftapi/fields.py
swiftapi/filters.py
swiftapi/generics.py
swiftapi/handlers.py
swiftapi/lifecycle.py
swiftapi/metadata.py
swiftapi/middleware.py
swiftapi/openapi.py
swiftapi/pagination.py
swiftapi/permissions.py
swiftapi/py.typed
swiftapi/relations.py
swiftapi/responses.py
swiftapi/reverse.py
swiftapi/routing.py
swiftapi/schemas.py
swiftapi/status.py
swiftapi/tasks.py
swiftapi/tenancy.py
swiftapi/testing.py
swiftapi/throttling.py
swiftapi/uploads.py
swiftapi/validators.py
swiftapi/versioning.py
swiftapi/viewsets.py
django_swiftapi_core-0.1.0.dist-info/METADATA
django_swiftapi_core-0.1.0.dist-info/WHEEL
django_swiftapi_core-0.1.0.dist-info/licenses/LICENSE
django_swiftapi_core-0.1.0.dist-info/RECORD
