Metadata-Version: 2.4
Name: django-swiftapi-core
Version: 0.1.0
Summary: An async-first, high-performance API framework for Django - the modern successor to DRF
Project-URL: Homepage, https://github.com/kkrajid/django-swiftapi
Project-URL: Documentation, https://github.com/kkrajid/django-swiftapi#readme
Project-URL: Repository, https://github.com/kkrajid/django-swiftapi
Project-URL: Changelog, https://github.com/kkrajid/django-swiftapi/blob/main/CHANGELOG.md
Author-email: RAJID K K <rajidkk34@gmail.com>
License: MIT
License-File: LICENSE
Keywords: api,async,django,framework,multi-tenant,openapi,rest,rest-framework,schema,swagger,viewset
Classifier: Development Status :: 3 - Alpha
Classifier: Environment :: Web Environment
Classifier: Framework :: Django
Classifier: Framework :: Django :: 4.2
Classifier: Framework :: Django :: 5.0
Classifier: Framework :: Django :: 5.1
Classifier: Intended Audience :: Developers
Classifier: License :: OSI Approved :: MIT License
Classifier: Operating System :: OS Independent
Classifier: Programming Language :: Python :: 3
Classifier: Programming Language :: Python :: 3.10
Classifier: Programming Language :: Python :: 3.11
Classifier: Programming Language :: Python :: 3.12
Classifier: Programming Language :: Python :: 3.13
Classifier: Topic :: Internet :: WWW/HTTP
Classifier: Topic :: Internet :: WWW/HTTP :: Dynamic Content
Classifier: Topic :: Software Development :: Libraries :: Application Frameworks
Classifier: Typing :: Typed
Requires-Python: >=3.10
Requires-Dist: django>=4.2
Provides-Extra: all
Requires-Dist: django-swiftapi[jwt,orjson,redis]; extra == 'all'
Provides-Extra: dev
Requires-Dist: django-stubs>=4.2.0; extra == 'dev'
Requires-Dist: httpx>=0.25.0; extra == 'dev'
Requires-Dist: mypy>=1.5.0; extra == 'dev'
Requires-Dist: pre-commit>=3.4.0; extra == 'dev'
Requires-Dist: pytest-asyncio>=0.21.0; extra == 'dev'
Requires-Dist: pytest-cov>=4.1.0; extra == 'dev'
Requires-Dist: pytest-django>=4.5.0; extra == 'dev'
Requires-Dist: pytest>=7.4.0; extra == 'dev'
Requires-Dist: ruff>=0.1.0; extra == 'dev'
Provides-Extra: docs
Requires-Dist: myst-parser>=2.0.0; extra == 'docs'
Requires-Dist: sphinx-rtd-theme>=1.3.0; extra == 'docs'
Requires-Dist: sphinx>=7.0.0; extra == 'docs'
Provides-Extra: jwt
Requires-Dist: pyjwt>=2.8.0; extra == 'jwt'
Provides-Extra: orjson
Requires-Dist: orjson>=3.9.0; extra == 'orjson'
Provides-Extra: redis
Requires-Dist: redis>=5.0.0; extra == 'redis'
